fxp/__init__.py
fxp/py.typed
fxp-0.1.0.dist-info/LICENSE
fxp-0.1.0.dist-info/METADATA
fxp-0.1.0.dist-info/WHEEL
fxp-0.1.0.dist-info/top_level.txt
fxp-0.1.0.dist-info/RECORD
