Metadata-Version: 2.1
Name: fxp
Version: 0.1.0
Summary: VST2.x plugin FXP preset parser
Home-page: https://github.com/demberto/fxp
Author: demberto
Author-email: demberto@protonmail.com
License: MIT
Project-URL: Source, https://github.com/demberto/fxp
Project-URL: Changelog, https://github.com/demberto/fxp/blob/master/CHANGELOG.md
Project-URL: Documentation, https://fxp.rtfd.io
Project-URL: Bug Tracker, https://github.com/demberto/fxp/issues
Platform: UNKNOWN
Classifier: Development Status :: 3 - Alpha
Classifier: License :: OSI Approved :: MIT License
Classifier: Operating System :: OS Independent
Classifier: Programming Language :: Python :: 3
Classifier: Programming Language :: Python :: 3 :: Only
Classifier: Programming Language :: Python :: 3.6
Classifier: Programming Language :: Python :: 3.7
Classifier: Programming Language :: Python :: 3.8
Classifier: Programming Language :: Python :: 3.9
Classifier: Programming Language :: Python :: 3.10
Requires-Python: >=3.6
License-File: LICENSE
